geogridfusion/__init__.py
geogridfusion/config.py
geogridfusion/core.py
geogridfusion/initdb.py
geogridfusion/queries.py
geogridfusion/sandbox.ipynb
geogridfusion/startup.py
geogridfusion/tables.py
geogridfusion/utilities.py
geogridfusion/watchdog.py
geogridfusion-0.1.1.dist-info/licenses/LICENSE.md
geogridfusion-0.1.1.dist-info/METADATA
geogridfusion-0.1.1.dist-info/WHEEL
geogridfusion-0.1.1.dist-info/top_level.txt
geogridfusion-0.1.1.dist-info/RECORD
