Metadata-Version: 2.4
Name: geogridfusion
Version: 0.1.1
Author-email: Tobin Ford <tobin.ford@nrel.gov>
License: BSD-3
Classifier: Development Status :: 4 - Beta
Classifier: Operating System :: OS Independent
Classifier: Intended Audience :: Science/Research
Classifier: Programming Language :: Python :: 3
Classifier: Topic :: Scientific/Engineering
Requires-Python: >=3.9.0
License-File: LICENSE.md
Requires-Dist: xarray
Requires-Dist: dask
Requires-Dist: dask[distributed]
Requires-Dist: pandas
Requires-Dist: numpy
Requires-Dist: scipy
Requires-Dist: zarr
Requires-Dist: h5py
Requires-Dist: pyproj
Requires-Dist: IPython
Requires-Dist: pyyaml
Requires-Dist: psycopg2
Requires-Dist: importlib_metadata
Provides-Extra: docs
Requires-Dist: readthedocs-sphinx-search<0.4,>=0.3.1; extra == "docs"
Requires-Dist: sphinx<8,>=7.2.6; extra == "docs"
Requires-Dist: sphinx_rtd_theme<3,>=2.0.0; extra == "docs"
Requires-Dist: sphinx-gallery; extra == "docs"
Requires-Dist: nbsphinx; extra == "docs"
Requires-Dist: sphinx_toggleprompt; extra == "docs"
Requires-Dist: pydata_sphinx_theme; extra == "docs"
Requires-Dist: mistune==3.0.0; extra == "docs"
Provides-Extra: test
Requires-Dist: pytest; extra == "test"
Requires-Dist: pytest-cov; extra == "test"
Provides-Extra: dev
Requires-Dist: build; extra == "dev"
Requires-Dist: flake8; extra == "dev"
Provides-Extra: all
Requires-Dist: geogridstore[build,dev,docs,test]; extra == "all"
Dynamic: license-file
